{"cameraMode":{"drawMode":0,"name":"Shaded","section":"Shading Mode"},"sceneLighting":true,"audioPlay":false,"sceneViewState":{"m_AlwaysRefresh":false,"showFog":true,"showSkybox":true,"showFlares":true,"showImageEffects":true,"showParticleSystems":true,"showVisualEffectGraphs":true,"m_FxEnabled":true},"in2DMode":false,"pivot":{"x":14.951705932617188,"y":11.78081226348877,"z":8.045923233032227},"rotation":{"x":0.3999885618686676,"y":-0.06179133430123329,"z":0.027040518820285798,"w":0.9140357375144959},"size":38.45539855957031,"orthographic":false}